pylll/__init__.py
pylll/decision.py
pylll/generator.py
pylll/solver.py
satlll/__init__.py
satlll/decision.py
satlll/generator.py
satlll/solver.py
satlll-0.1.0.dist-info/LICENSE
satlll-0.1.0.dist-info/METADATA
satlll-0.1.0.dist-info/WHEEL
satlll-0.1.0.dist-info/top_level.txt
satlll-0.1.0.dist-info/RECORD
